.gitlab-ci.yml
AUTHORS
ChangeLog
LICENSE
README.rst
requirements.txt
setup.cfg
setup.py
test-requirements.txt
tox.ini
apt_deps/__init__.py
apt_deps/get_deps.py
apt_deps.egg-info/PKG-INFO
apt_deps.egg-info/SOURCES.txt
apt_deps.egg-info/dependency_links.txt
apt_deps.egg-info/entry_points.txt
apt_deps.egg-info/not-zip-safe
apt_deps.egg-info/pbr.json
apt_deps.egg-info/requires.txt
apt_deps.egg-info/top_level.txt
tests/test_get_deps.py