Metadata-Version: 1.1
Name: apt-deps
Version: 1.0.0
Summary: Recursive dependencies for apt
Home-page: https://gitlab.com/michaelgugino/apt-deps
Author: OpenStack
Author-email: gugino.michael@yahoo.com
License: UNKNOWN
Platform: Linux
Classifier: Environment :: Console
Classifier: Intended Audience :: Information Technology
Classifier: Intended Audience :: System Administrators
Classifier: License :: OSI Approved :: Apache Software License
Classifier: Operating System :: POSIX :: Linux
Classifier: Programming Language :: Python
Classifier: Programming Language :: Python :: 2
Classifier: Programming Language :: Python :: 2.6
Classifier: Programming Language :: Python :: 2.7
Classifier: Programming Language :: Python :: 3.4
Classifier: Programming Language :: Python :: 3.5
